{
	"fem": {
		"version": "1.0",
		"type": "3D solid"
	},

	"materials": [
		{"type":"linear elastic", "label": "Steel", "E":200e+06,"nu":0.3, "fy": 2e+07}
	],

	"nodes":[
		[1,[0,0,	-1]],
		[2,[1,0,	-1]],
		[3,[0,1,	-1]],
		[4,[0,0,	1]],
		[5,[1,0,	1]],
		[6,[-0.25,1.25,1.25]],
		[7,[0.5,0,	-1]],
		[8,[0,0.5,	-1]],
		[9,[0,0,	0]],
		[10,[0.5,0.5,	-1]],
		[11,[1,0,	0]],
		[12,[0,1,	0]],
		[13,[0.5,0,	1]],
		[14,[0,0.5,	1]],
		[15,[0.5,0.5,	1]]
	],

	"elements":[
		{"type":"prism15", "nodes":[1,2,3,4,5,6,7,8,9,10,11,12,13,14,15], "material": 0}
	],

	"node restrictions": [
		{ "node": 1, "dx":true, "dy":true, "dz":true},
		{ "node": 2, "dx":true, "dy":true, "dz":true},
		{ "node": 3, "dx":true, "dy":true, "dz":true},
		{ "node": 7, "dx":true, "dy":true, "dz":true},
		{ "node":10, "dx":true, "dy":true, "dz":true},
		{ "node": 8, "dx":true, "dy":true, "dz":true},
	],

	"load patterns":[
		{
			"label": "First test pattern",

			"nodal loads":[
				{"node":6, "force":[1, 0, 0]}
			],

			"domain loads":[
				{"element":0, "force": [1,1,1]}
			],

			"surface loads":[
				{"type": "quadrangle8", "nodes": [2, 3, 6, 5, 10, 12, 15, 11], "forces": [[1,1,1],[1,1,1],[1,1,1],[1,1,1],[1,1,1],[1,1,1],[1,1,1],[1,1,1]]}
			]

		}
	]

}
